lifeguard_simple_dashboard/__init__.py
lifeguard_simple_dashboard/settings.py
lifeguard_simple_dashboard/controllers/__init__.py
lifeguard_simple_dashboard/controllers/index_controller.py
lifeguard_simple_dashboard/public/css/dashboard.css
lifeguard_simple_dashboard/public/img/wallpaper.jpg
lifeguard_simple_dashboard/templates/dashboard.html
lifeguard_simple_dashboard-1.0.0.dist-info/METADATA
lifeguard_simple_dashboard-1.0.0.dist-info/WHEEL
lifeguard_simple_dashboard-1.0.0.dist-info/top_level.txt
lifeguard_simple_dashboard-1.0.0.dist-info/RECORD
