Metadata-Version: 2.1
Name: lifeguard-simple-dashboard
Version: 1.0.0
Summary: Implementation of a simple Lifeguard Dashboard
Home-page: https://github.com/LifeguardSystem/lifeguard-simple-dashboard
Author: Diego Rubin
Author-email: contact@diegorubin.dev
License: GPL2
Classifier: Development Status :: 3 - Alpha
Requires-Dist: lifeguard
